auto_media_platform/__init__.py
auto_media_platform/main.py
auto_media_platform-0.0.3.dist-info/LICENSE
auto_media_platform-0.0.3.dist-info/METADATA
auto_media_platform-0.0.3.dist-info/WHEEL
auto_media_platform-0.0.3.dist-info/entry_points.txt
auto_media_platform-0.0.3.dist-info/RECORD
