Metadata-Version: 2.1
Name: auto-media-platform
Version: 0.0.3
Summary: generate video and upload to multiple media platform automatically
Home-page: https://github.com/idlewith/auto_media_platform
License: MIT
Author: idlewith
Author-email: newellzhou@163.com
Requires-Python: >=3.7,<4
Classifier: Development Status :: 1 - Planning
Classifier: Environment :: Console
Classifier: Intended Audience :: End Users/Desktop
Classifier: License :: OSI Approved :: MIT License
Classifier: Natural Language :: English
Classifier: Operating System :: OS Independent
Classifier: Programming Language :: Python :: 3
Classifier: Programming Language :: Python :: 3.7
Classifier: Programming Language :: Python :: 3.8
Classifier: Programming Language :: Python :: 3.9
Classifier: Programming Language :: Python :: 3.10
Classifier: Programming Language :: Python :: 3.11
